funcnodes_sec/__init__.py
funcnodes_sec/read_data.py
funcnodes_sec/report.py
funcnodes_sec/__pycache__/__init__.cpython-312.pyc
funcnodes_sec/__pycache__/read_data.cpython-312.pyc
funcnodes_sec/__pycache__/report.cpython-312.pyc
funcnodes_sec-0.1.8.dist-info/licenses/LICENSE
funcnodes_sec-0.1.8.dist-info/METADATA
funcnodes_sec-0.1.8.dist-info/WHEEL
funcnodes_sec-0.1.8.dist-info/entry_points.txt
funcnodes_sec-0.1.8.dist-info/top_level.txt
funcnodes_sec-0.1.8.dist-info/RECORD
