Metadata-Version: 2.4
Name: funcnodes-sec
Version: 0.1.8
Author-email: Kourosh Rezaei <kourosh.rezaei@linkdlab.de>
License: AGPL-3.0
Project-URL: homepage, https://github.com/Linkdlab/funcnodes_sec
Project-URL: source, https://github.com/Linkdlab/funcnodes_sec
Project-URL: tracker, https://github.com/Linkdlab/funcnodes_sec/issues
Project-URL: download, https://pypi.org/project/funcnodes-sec/#files
Classifier: License :: OSI Approved :: GNU Affero General Public License v3 or later (AGPLv3+)
Classifier: Programming Language :: Python :: 3
Requires-Python: >=3.11
License-File: LICENSE
Requires-Dist: funcnodes
Requires-Dist: funcnodes-span
Requires-Dist: funcnodes-pandas
Requires-Dist: pip>=24.2
Dynamic: license-file
